avirtech_spraying_lib/__init__.py
avirtech_spraying_lib/avir_palm_corr.py
avirtech_spraying_lib-0.1.1.dist-info/METADATA
avirtech_spraying_lib-0.1.1.dist-info/WHEEL
avirtech_spraying_lib-0.1.1.dist-info/top_level.txt
avirtech_spraying_lib-0.1.1.dist-info/RECORD
